{
  "hash": "81062ed6",
  "configHash": "da959e50",
  "lockfileHash": "b958b8cf",
  "browserHash": "4a62f927",
  "optimized": {
    "vue": {
      "src": "../../../node_modules/vue/dist/vue.runtime.esm-bundler.js",
      "file": "vue.js",
      "fileHash": "2942e1c1",
      "needsInterop": false
    },
    "vitepress > @vue/devtools-api": {
      "src": "../../../node_modules/@vue/devtools-api/dist/index.js",
      "file": "vitepress___@vue_devtools-api.js",
      "fileHash": "0ad38b73",
      "needsInterop": false
    },
    "vitepress > @vueuse/core": {
      "src": "../../../node_modules/@vueuse/core/index.mjs",
      "file": "vitepress___@vueuse_core.js",
      "fileHash": "8d2bd11e",
      "needsInterop": false
    },
    "@theme/index": {
      "src": "../../../node_modules/vitepress/dist/client/theme-default/index.js",
      "file": "@theme_index.js",
      "fileHash": "bf11bb29",
      "needsInterop": false
    }
  },
  "chunks": {
    "chunk-VVKHXDAH": {
      "file": "chunk-VVKHXDAH.js"
    },
    "chunk-GH2C7TZD": {
      "file": "chunk-GH2C7TZD.js"
    }
  }
}